<Properties StartupConfiguration="{CA7EF4F0-D6B3-431A-A088-666A9E0C17FE}|Default">
  <MonoDevelop.Ide.ItemProperties.PulluBackEnd PreferredExecutionTarget="/Applications/Safari.app" />
  <MonoDevelop.Ide.Workbench ActiveDocument="Controllers/App/androidmobileappController.cs">
    <Files>
      <File FileName="Model/Database/App/DbInsert.cs" Line="1050" Column="60" IsPinned="True" />
      <File FileName="Controllers/App/androidmobileappController.cs" Line="101" Column="14" />
      <File FileName="Model/Database/App/DbSelect.cs" Line="792" Column="68" />
      <File FileName="Model/App/server/User.cs" />
      <File FileName="Model/App/server/ResponseStruct.cs" />
      <File FileName="Model/App/server/FinanceStruct.cs" />
      <File FileName="Model/Database/Admin/DbInsert.cs" />
      <File FileName="Model/CommonScripts/Communication.cs" />
      <File FileName="Model/App/server/SignInStruct.cs" />
      <File FileName="Model/CommonScripts/Security.cs" />
      <File FileName="Model/App/client/NewUserStruct.cs" />
      <File FileName="Model/App/server/Status.cs" />
      <File FileName="Model/App/client/NewAdvertisementStruct.cs" />
      <File FileName="Model/App/client/UpdateProfileStruct.cs" />
      <File FileName="Model/App/server/ProfileStruct.cs" />
      <File FileName="Properties/launchSettings.json" />
      <File FileName="Model/App/client/NewUser.cs" />
    </Files>
    <Pads>
      <Pad Id="ProjectPad">
        <State name="__root__">
          <Node name="PulluBackEnd" expanded="True">
            <Node name="PulluBackEnd" expanded="True" selected="True">
              <Node name="Controllers" expanded="True">
                <Node name="App" expanded="True" />
              </Node>
              <Node name="Model" expanded="True">
                <Node name="App" expanded="True">
                  <Node name="client" expanded="True" />
                </Node>
                <Node name="CommonScripts" expanded="True" />
                <Node name="Database" expanded="True">
                  <Node name="App" expanded="True" />
                </Node>
              </Node>
              <Node name="Properties" expanded="True" />
              <Node name="wwwroot" expanded="True" />
            </Node>
          </Node>
        </State>
      </Pad>
    </Pads>
  </MonoDevelop.Ide.Workbench>
  <MonoDevelop.Ide.DebuggingService.PinnedWatches />
  <MonoDevelop.Ide.Workspace ActiveConfiguration="Debug" />
  <MonoDevelop.Ide.DebuggingService.Breakpoints>
    <BreakpointStore>
      <Breakpoint file="/usr/local/share/dotnet/sdk/3.1.401/Sdks/Microsoft.NET.Sdk/targets/Microsoft.PackageDependencyResolution.targets" line="241" column="5" />
      <Breakpoint file="/Users/rufat/Desktop/PulluBackEnd/Controllers/App/androidmobileappController.cs" relfile="Controllers/App/androidmobileappController.cs" line="515" column="1" />
      <Breakpoint file="/Users/rufat/Desktop/PulluBackEnd/Controllers/App/androidmobileappController.cs" relfile="Controllers/App/androidmobileappController.cs" line="697" column="1" />
      <Breakpoint file="/Users/rufat/Desktop/PulluBackEnd/Model/Database/App/DbInsert.cs" relfile="Model/Database/App/DbInsert.cs" line="394" column="1" />
      <Breakpoint file="/Users/rufat/Desktop/PulluBackEnd/Model/Database/App/DbSelect.cs" relfile="Model/Database/App/DbSelect.cs" line="148" column="1" />
    </BreakpointStore>
  </MonoDevelop.Ide.DebuggingService.Breakpoints>
  <MultiItemStartupConfigurations />
</Properties>